ampligraph/__init__.py
ampligraph/logger.conf
ampligraph/compat/__init__.py
ampligraph/compat/evaluate.py
ampligraph/compat/models.py
ampligraph/datasets/__init__.py
ampligraph/datasets/data_adapter.py
ampligraph/datasets/data_indexer.py
ampligraph/datasets/datasets.py
ampligraph/datasets/graph_data_loader.py
ampligraph/datasets/graph_partitioner.py
ampligraph/datasets/partitioned_data_manager.py
ampligraph/datasets/partitioning_reporter.py
ampligraph/datasets/source_identifier.py
ampligraph/datasets/sqlite_adapter.py
ampligraph/discovery/__init__.py
ampligraph/discovery/discovery.py
ampligraph/evaluation/__init__.py
ampligraph/evaluation/metrics.py
ampligraph/evaluation/protocol.py
ampligraph/latent_features/__init__.py
ampligraph/latent_features/loss_functions.py
ampligraph/latent_features/optimizers.py
ampligraph/latent_features/regularizers.py
ampligraph/latent_features/layers/__init__.py
ampligraph/latent_features/layers/calibration/__init__.py
ampligraph/latent_features/layers/calibration/calibrate.py
ampligraph/latent_features/layers/corruption_generation/CorruptionGenerationLayerTrain.py
ampligraph/latent_features/layers/corruption_generation/__init__.py
ampligraph/latent_features/layers/encoding/EmbeddingLookupLayer.py
ampligraph/latent_features/layers/encoding/__init__.py
ampligraph/latent_features/layers/scoring/AbstractScoringLayer.py
ampligraph/latent_features/layers/scoring/ComplEx.py
ampligraph/latent_features/layers/scoring/DistMult.py
ampligraph/latent_features/layers/scoring/HolE.py
ampligraph/latent_features/layers/scoring/Random.py
ampligraph/latent_features/layers/scoring/RotatE.py
ampligraph/latent_features/layers/scoring/TransE.py
ampligraph/latent_features/layers/scoring/__init__.py
ampligraph/latent_features/models/NodePiece.py
ampligraph/latent_features/models/ScoringBasedEmbeddingModel.py
ampligraph/latent_features/models/__init__.py
ampligraph/pretrained_models/__init__.py
ampligraph/pretrained_models/pretrained_utils.py
ampligraph-2.1.0.dist-info/LICENSE
ampligraph-2.1.0.dist-info/METADATA
ampligraph-2.1.0.dist-info/WHEEL
ampligraph-2.1.0.dist-info/top_level.txt
ampligraph-2.1.0.dist-info/RECORD
